{
  "name": "Belarus",
  "data": [
    {
      "year": "1992",
      "bottom": 0.0,
      "middle": 0.0,
      "top": 0.0
    },
    {
      "year": "1993",
      "bottom": 0.0,
      "middle": 0.0,
      "top": 0.0
    },
    {
      "year": "1994",
      "bottom": 0.0,
      "middle": 0.0,
      "top": 0.0
    },
    {
      "year": "1995",
      "bottom": 0.0,
      "middle": 0.0,
      "top": 0.0
    },
    {
      "year": "1996",
      "bottom": 0.0,
      "middle": 0.0,
      "top": 0.0
    },
    {
      "year": "1997",
      "bottom": 0.0,
      "middle": 0.0,
      "top": 0.0
    },
    {
      "year": "1998",
      "bottom": 2704.3791866216607,
      "middle": 17800.976924598275,
      "top": 13727.291820699822
    },
    {
      "year": "1999",
      "bottom": 2706.6932877245686,
      "middle": 18875.624243342387,
      "top": 14032.06783373
    },
    {
      "year": "2000",
      "bottom": 2990.0619688328266,
      "middle": 20059.909411156936,
      "top": 14798.91430143842
    },
    {
      "year": "2001",
      "bottom": 3265.556848694888,
      "middle": 21066.824060482875,
      "top": 15491.483099296483
    },
    {
      "year": "2002",
      "bottom": 3499.920796619619,
      "middle": 22306.72411339492,
      "top": 16361.075531185686
    },
    {
      "year": "2003",
      "bottom": 3919.339730034734,
      "middle": 24518.660171612646,
      "top": 17135.717889454187
    },
    {
      "year": "2004",
      "bottom": 4806.0872293270795,
      "middle": 27967.337387679927,
      "top": 18355.162929025762
    },
    {
      "year": "2005",
      "bottom": 5015.660622379331,
      "middle": 30770.232582237237,
      "top": 20569.84412548826
    },
    {
      "year": "2006",
      "bottom": 5464.637882734277,
      "middle": 33595.10334726413,
      "top": 23038.416528345642
    },
    {
      "year": "2007",
      "bottom": 5793.256893633985,
      "middle": 35702.629693325725,
      "top": 25867.565664598264
    },
    {
      "year": "2008",
      "bottom": 6673.541408889261,
      "middle": 40189.54937353311,
      "top": 27287.3693163472
    },
    {
      "year": "2009",
      "bottom": 6721.29861782456,
      "middle": 39810.76873634548,
      "top": 27328.357017528433
    },
    {
      "year": "2010",
      "bottom": 7034.868426469553,
      "middle": 42928.68573879714,
      "top": 29978.132499160023
    },
    {
      "year": "2011",
      "bottom": 7734.904216429121,
      "middle": 45820.89997775947,
      "top": 30519.241636562725
    },
    {
      "year": "2012",
      "bottom": 8106.0850760349385,
      "middle": 46418.00296171586,
      "top": 30803.123288932766
    },
    {
      "year": "2013",
      "bottom": 8061.280366375228,
      "middle": 46076.581462544724,
      "top": 30717.72097502982
    },
    {
      "year": "2014",
      "bottom": 8100.40574468788,
      "middle": 47034.61400141348,
      "top": 31966.117293553245
    },
    {
      "year": "2015",
      "bottom": 8010.0276902612095,
      "middle": 45252.527569723134,
      "top": 29315.049794254945
    },
    {
      "year": "2016",
      "bottom": 7984.890554965603,
      "middle": 44037.881242537565,
      "top": 28632.68835366453
    },
    {
      "year": "2017",
      "bottom": 8230.605508999643,
      "middle": 45393.03644357379,
      "top": 29513.78743126134
    }
  ],
  "colors": [
    "#d4d9b7",
    "#d4d9b7",
    "#d4d9b7",
    "#d4d9b7",
    "#d4d9b7",
    "#d4d9b7",
    "#edc066",
    "#f5e193",
    "#f5e193",
    "#f5e193",
    "#f5e193",
    "#f5e193",
    "#f5e193",
    "#f5e193",
    "#f5e193",
    "#f5e193",
    "#f5e193",
    "#f5e193",
    "#f5e193",
    "#f5e193",
    "#f5e193",
    "#f5e193",
    "#f5e193",
    "#f5e193",
    "#f5e193",
    "#f5e193"
  ]
}