{
  "name": "Ireland",
  "data": [
    {
      "year": "1992",
      "bottom": 0.0,
      "middle": 0.0,
      "top": 0.0
    },
    {
      "year": "1993",
      "bottom": 0.0,
      "middle": 0.0,
      "top": 0.0
    },
    {
      "year": "1994",
      "bottom": 0.0,
      "middle": 0.0,
      "top": 0.0
    },
    {
      "year": "1995",
      "bottom": 0.0,
      "middle": 0.0,
      "top": 0.0
    },
    {
      "year": "1996",
      "bottom": 0.0,
      "middle": 0.0,
      "top": 0.0
    },
    {
      "year": "1997",
      "bottom": 0.0,
      "middle": 0.0,
      "top": 0.0
    },
    {
      "year": "1998",
      "bottom": 0.0,
      "middle": 0.0,
      "top": 0.0
    },
    {
      "year": "1999",
      "bottom": 0.0,
      "middle": 0.0,
      "top": 0.0
    },
    {
      "year": "2000",
      "bottom": 0.0,
      "middle": 0.0,
      "top": 0.0
    },
    {
      "year": "2001",
      "bottom": 0.0,
      "middle": 0.0,
      "top": 0.0
    },
    {
      "year": "2002",
      "bottom": 0.0,
      "middle": 0.0,
      "top": 0.0
    },
    {
      "year": "2003",
      "bottom": 16311.042286213418,
      "middle": 36364.44492380914,
      "top": 86427.34094513083
    },
    {
      "year": "2004",
      "bottom": 16863.678706977167,
      "middle": 37795.35008449707,
      "top": 91640.78034186276
    },
    {
      "year": "2005",
      "bottom": 17721.45934763951,
      "middle": 38741.71848726386,
      "top": 96202.20788718591
    },
    {
      "year": "2006",
      "bottom": 18675.35598480445,
      "middle": 40502.67078560966,
      "top": 96213.54285842292
    },
    {
      "year": "2007",
      "bottom": 19813.084523254754,
      "middle": 41478.61190843984,
      "top": 97374.0617423374
    },
    {
      "year": "2008",
      "bottom": 18649.15174571913,
      "middle": 39800.01896952254,
      "top": 89379.47117155633
    },
    {
      "year": "2009",
      "bottom": 16532.992541581007,
      "middle": 36930.84048249263,
      "top": 87388.67486264245
    },
    {
      "year": "2010",
      "bottom": 16535.608986561325,
      "middle": 37857.84162712724,
      "top": 87464.66858681123
    },
    {
      "year": "2011",
      "bottom": 16851.58386158769,
      "middle": 38796.09084578855,
      "top": 91447.92842221589
    },
    {
      "year": "2012",
      "bottom": 16810.975753277562,
      "middle": 38403.74016526519,
      "top": 92124.14712796104
    },
    {
      "year": "2013",
      "bottom": 16494.35801539176,
      "middle": 38712.785479047336,
      "top": 93317.39534735339
    },
    {
      "year": "2014",
      "bottom": 19279.508494791262,
      "middle": 42301.031296588415,
      "top": 97861.80894191514
    },
    {
      "year": "2015",
      "bottom": 24197.619097860315,
      "middle": 52226.527886215175,
      "top": 121593.03596674808
    },
    {
      "year": "2016",
      "bottom": 0.0,
      "middle": 0.0,
      "top": 0.0
    },
    {
      "year": "2017",
      "bottom": 0.0,
      "middle": 0.0,
      "top": 0.0
    }
  ]
}