{
  "name": "Spain",
  "data": [
    {
      "year": "1992",
      "bottom": 0.0,
      "middle": 0.0,
      "top": 0.0
    },
    {
      "year": "1993",
      "bottom": 0.0,
      "middle": 0.0,
      "top": 0.0
    },
    {
      "year": "1994",
      "bottom": 0.0,
      "middle": 0.0,
      "top": 0.0
    },
    {
      "year": "1995",
      "bottom": 0.0,
      "middle": 0.0,
      "top": 0.0
    },
    {
      "year": "1996",
      "bottom": 0.0,
      "middle": 0.0,
      "top": 0.0
    },
    {
      "year": "1997",
      "bottom": 0.0,
      "middle": 0.0,
      "top": 0.0
    },
    {
      "year": "1998",
      "bottom": 0.0,
      "middle": 0.0,
      "top": 0.0
    },
    {
      "year": "1999",
      "bottom": 0.0,
      "middle": 0.0,
      "top": 0.0
    },
    {
      "year": "2000",
      "bottom": 0.0,
      "middle": 0.0,
      "top": 0.0
    },
    {
      "year": "2001",
      "bottom": 0.0,
      "middle": 0.0,
      "top": 0.0
    },
    {
      "year": "2002",
      "bottom": 0.0,
      "middle": 0.0,
      "top": 0.0
    },
    {
      "year": "2003",
      "bottom": 11453.551682101128,
      "middle": 28474.802098556964,
      "top": 62199.148718076955
    },
    {
      "year": "2004",
      "bottom": 11130.198349939563,
      "middle": 28390.071153469027,
      "top": 65006.81065254555
    },
    {
      "year": "2005",
      "bottom": 11515.695706280703,
      "middle": 29282.769081685215,
      "top": 65145.93570981655
    },
    {
      "year": "2006",
      "bottom": 11289.785458236387,
      "middle": 29712.917947298745,
      "top": 68075.72127055969
    },
    {
      "year": "2007",
      "bottom": 11500.4317461041,
      "middle": 29924.008971206185,
      "top": 70375.77635675643
    },
    {
      "year": "2008",
      "bottom": 11274.102309091173,
      "middle": 29836.51318163523,
      "top": 70036.09010193
    },
    {
      "year": "2009",
      "bottom": 10285.541337410184,
      "middle": 28462.106452198554,
      "top": 67590.70021726693
    },
    {
      "year": "2010",
      "bottom": 10239.734599309792,
      "middle": 28172.814770587782,
      "top": 67777.290919241
    },
    {
      "year": "2011",
      "bottom": 9620.481278193254,
      "middle": 27952.842824972613,
      "top": 66862.34488344312
    },
    {
      "year": "2012",
      "bottom": 9488.302176798816,
      "middle": 27116.841740250162,
      "top": 64707.10992702144
    },
    {
      "year": "2013",
      "bottom": 8743.491429642565,
      "middle": 26792.921106039204,
      "top": 64272.33173719709
    },
    {
      "year": "2014",
      "bottom": 8890.690494027984,
      "middle": 27243.98724485768,
      "top": 65354.37398241622
    },
    {
      "year": "2015",
      "bottom": 9383.667472787905,
      "middle": 28097.073294956885,
      "top": 68112.48286282257
    },
    {
      "year": "2016",
      "bottom": 0.0,
      "middle": 0.0,
      "top": 0.0
    },
    {
      "year": "2017",
      "bottom": 0.0,
      "middle": 0.0,
      "top": 0.0
    }
  ]
}